tap_quickbooks_report/__init__.py
tap_quickbooks_report/streams.py
tap_quickbooks_report/utils.py
tap_quickbooks_report/version.py
tap_quickbooks_report/schemas/profit_and_loss.json
tap_quickbooks_report/schemas/profit_and_loss_detail.json
tap_quickbooks_report-0.1.2.dist-info/LICENSE
tap_quickbooks_report-0.1.2.dist-info/METADATA
tap_quickbooks_report-0.1.2.dist-info/WHEEL
tap_quickbooks_report-0.1.2.dist-info/entry_points.txt
tap_quickbooks_report-0.1.2.dist-info/top_level.txt
tap_quickbooks_report-0.1.2.dist-info/RECORD
